exit_speed/__init__.py
exit_speed/accelerometer.py
exit_speed/accelerometer_test.py
exit_speed/cleanup_timescale.py
exit_speed/common_lib.py
exit_speed/common_lib_test.py
exit_speed/config_lib.py
exit_speed/convert_data_to_csv.py
exit_speed/csv_lib.py
exit_speed/data_logger.py
exit_speed/data_logger_test.py
exit_speed/gcs_archive.py
exit_speed/gps_pb2.py
exit_speed/gps_sensor.py
exit_speed/gps_sensor_test.py
exit_speed/gyroscope.py
exit_speed/gyroscope_test.py
exit_speed/labjack.py
exit_speed/labjack_test.py
exit_speed/lap_lib.py
exit_speed/lap_lib_test.py
exit_speed/leds.py
exit_speed/leds_test.py
exit_speed/main.py
exit_speed/main_test.py
exit_speed/replay_data.py
exit_speed/replay_data_test.py
exit_speed/sensor.py
exit_speed/sensor_test.py
exit_speed/sync_local_data.py
exit_speed/timescale.py
exit_speed/timescale_test.py
exit_speed/tire_temperature.py
exit_speed/tire_temperature_test.py
exit_speed/tracks_test.py
exit_speed/wbo2.py
exit_speed/wbo2_test.py
exit_speed/dashboard/__init__.py
exit_speed/dashboard/main.py
exit_speed/dashboard/queries.py
exit_speed/tracks/__init__.py
exit_speed/tracks/area27.py
exit_speed/tracks/base.py
exit_speed/tracks/oregon_raceway_park.py
exit_speed/tracks/pacific_raceways.py
exit_speed/tracks/portland_internal_raceways.py
exit_speed/tracks/spokane_raceway.py
exit_speed/tracks/test_track.py
exit_speed/tracks/the_ridge.py
exit_speed-2022.1.20.dist-info/LICENSE
exit_speed-2022.1.20.dist-info/METADATA
exit_speed-2022.1.20.dist-info/WHEEL
exit_speed-2022.1.20.dist-info/top_level.txt
exit_speed-2022.1.20.dist-info/RECORD
