Metadata-Version: 2.1
Name: exit-speed
Version: 2022.1.20
Summary: Race car telemetry with a Raspberry Pi
Home-page: https://github.com/djhedges/exit_speed
Author: Douglas Hedges
Author-email: djhedges+exit-speed@gmail.com
License: UNKNOWN
Project-URL: Travis CL, https://app.travis-ci.com/github/djhedges/exit_speed
Platform: UNKNOWN
Classifier: Programming Language :: Python :: 3
Classifier: Programming Language :: Python :: 3.7
Classifier: License :: OSI Approved :: Apache Software License
Requires-Python: >=3.7
License-File: LICENSE
Requires-Dist: absl-py (>=0.10.0)
Requires-Dist: gps (>=3.19)
Requires-Dist: protobuf (>=3.12.2)
Requires-Dist: pygatt (>=4.0.5)
Requires-Dist: python-geohash (>=0.8.5)
Requires-Dist: PyYAML (>=5.4)
Provides-Extra: cython_
Requires-Dist: 0.29.21 ; extra == 'cython_'
Provides-Extra: labjackpython_
Requires-Dist: 2.0.0 ; extra == 'labjackpython_'
Provides-Extra: rpi.gpio_
Requires-Dist: 0.7.0 ; extra == 'rpi.gpio_'
Provides-Extra: adafruit-circuitpython-busdevice_
Requires-Dist: 4.3.1 ; extra == 'adafruit-circuitpython-busdevice_'
Provides-Extra: adafruit-circuitpython-dotstar_
Requires-Dist: 2.0.0 ; extra == 'adafruit-circuitpython-dotstar_'
Provides-Extra: adafruit-circuitpython-fxas21002c_
Requires-Dist: 2.1.5 ; extra == 'adafruit-circuitpython-fxas21002c_'
Provides-Extra: adafruit-circuitpython-fxos8700_
Requires-Dist: 2.1.4 ; extra == 'adafruit-circuitpython-fxos8700_'
Provides-Extra: dash-core-components_
Requires-Dist: 2.0.0 ; extra == 'dash-core-components_'
Provides-Extra: dash-html-components_
Requires-Dist: 2.0.0 ; extra == 'dash-html-components_'
Provides-Extra: dash-table_
Requires-Dist: 5.0.0 ; extra == 'dash-table_'
Provides-Extra: dash_
Requires-Dist: 2.0.0 ; extra == 'dash_'
Provides-Extra: google-cloud-storage_
Requires-Dist: 1.43.0 ; extra == 'google-cloud-storage_'
Provides-Extra: grafanalib_
Requires-Dist: 0.6.1 ; extra == 'grafanalib_'
Provides-Extra: grpcio_
Requires-Dist: 1.18.0 ; extra == 'grpcio_'
Provides-Extra: matplotlib_
Requires-Dist: 3.0.2 ; extra == 'matplotlib_'
Provides-Extra: mlx9064x-driver_
Requires-Dist: 1.3.0 ; extra == 'mlx9064x-driver_'
Provides-Extra: numpy_
Requires-Dist: 1.21.0 ; extra == 'numpy_'
Provides-Extra: pandas_
Requires-Dist: 0.23.3 ; extra == 'pandas_'
Provides-Extra: plotly_
Requires-Dist: 5.4.0 ; extra == 'plotly_'
Provides-Extra: psycopg2_
Requires-Dist: 2.7.7 ; extra == 'psycopg2_'
Provides-Extra: scikit-learn_
Requires-Dist: 0.20.2 ; extra == 'scikit-learn_'
Provides-Extra: scipy_
Requires-Dist: 1.4.1 ; extra == 'scipy_'
Provides-Extra: sdnotify_
Requires-Dist: 0.3.2 ; extra == 'sdnotify_'
Provides-Extra: smbus2_
Requires-Dist: 0.4.1 ; extra == 'smbus2_'
